loggingpython/__init__.py
loggingpython/consolehandler.py
loggingpython/csvhandler.py
loggingpython/filehandler.py
loggingpython/handler.py
loggingpython/jsonhandler.py
loggingpython/log_levels.py
loggingpython/logger.py
loggingpython/sqlhandler.py
loggingpython/sys_procolls.py
loggingpython/sys_protocolls.py
loggingpython/error/__init__.py
loggingpython/error/client_method_call_error.py
loggingpython/error/handler_not_found_error.py
loggingpython/error/invalid_handler_method_error.py
loggingpython/error/invalid_log_level_error.py
loggingpython/error/server_method_call_error.py
loggingpython/error/server_unreachable_error.py
loggingpython/handler/__init__.py
loggingpython/handler/consolehandler.py
loggingpython/handler/csvhandler.py
loggingpython/handler/filehandler.py
loggingpython/handler/handler.py
loggingpython/handler/jsonhandler.py
loggingpython/handler/sqlhandler.py
loggingpython/handler/syshandler.py
loggingpython-1.4.17.dist-info/LICENSE
loggingpython-1.4.17.dist-info/METADATA
loggingpython-1.4.17.dist-info/WHEEL
loggingpython-1.4.17.dist-info/top_level.txt
loggingpython-1.4.17.dist-info/RECORD
