Metadata-Version: 2.1
Name: loggingpython
Version: 1.4.17
Summary: Loggingpython is a Python package that provides a simple and extensible way to integrate logging into your applications. The package starts with a simple logger and can be extended with additional functions to meet the requirements of your application.
Home-page: https://github.com/loggingpython-Community/loggingpython
Author: mrmajor.programmer
Author-email: mrmajork.programmer@gmail.com
License: MIT
Classifier: Development Status :: 3 - Alpha
Classifier: Intended Audience :: Developers
Classifier: License :: OSI Approved :: MIT License
Classifier: Programming Language :: Python :: 3
Classifier: Topic :: Software Development :: Libraries :: Python Modules
Classifier: Topic :: System :: Logging
License-File: LICENSE
Requires-Dist: colorama
Requires-Dist: pandas
